{
  "灵核": ["零和", "林河", "林科", "临河", "领和", "林和","宁河", "宁和", "灵和", "灵何", "灵禾", "灵赫", "灵荷", "灵合" ],
  "本源": ["100元", "百元"],
  "高灵": ["高岭", "高龄", "高陵", "高瓴", "高领"],
  "被催": ["悲催", "被吹", "背吹"],
  "互催": ["互吹"],
  "攻防系统": ["功放系统"],
  "心轮": ["兴隆"],
  "一灵": ["依琳", "伊琳", "依灵", "依林", "伊林", "依凌", "伊凌", "依零", "伊零"],
  "三灵": ["三菱", "三陵", "三领", "三零", "三林"],
  "自弱": ["自若"],
  "肉灵": ["若琳"],
  "肉体灵": ["肉体零", "肉体领", "肉体林", "肉体凌", "肉铁林", "陆铁林", "肉铁零", "肉绮玲", "肉铁凌"],
  "灵体": ["零体", "领体", "林体", "凌体", "零题"],
  "_regex": {
    "一灵": ["10", "衣灵", "衣领"],
    "二灵": ["20"],
    "三灵": ["30"],
    "四灵": ["40"],
    "五灵": ["50"],
    "六灵": ["60"],
    "七灵": ["70"],
    "八灵": ["80"],
    "九灵": ["90"],
    "十灵": ["石灵", "十陵", "拾零"]
  }
}
