{"nodes": [{"id": "d_code_zero_apps_api_internal_logic_listreviewhistorylogic_test_go", "label": "listreviewhistorylogic_test.go", "file_type": "code", "source_file": "D:\\code\\zero\\apps\\api\\internal\\logic\\listreviewhistorylogic_test.go", "source_location": "L1"}, {"id": "logic_listreviewhistorylogic_test_testbuildreviewhistorylistquerywithoutfilters", "label": "TestBuildReviewHistoryListQueryWithoutFilters()", "file_type": "code", "source_file": "D:\\code\\zero\\apps\\api\\internal\\logic\\listreviewhistorylogic_test.go", "source_location": "L11"}, {"id": "logic_listreviewhistorylogic_test_testbuildreviewhistorylistquerywithfilters", "label": "TestBuildReviewHistoryListQueryWithFilters()", "file_type": "code", "source_file": "D:\\code\\zero\\apps\\api\\internal\\logic\\listreviewhistorylogic_test.go", "source_location": "L25"}], "edges": [{"source": "d_code_zero_apps_api_internal_logic_listreviewhistorylogic_test_go", "target": "go_pkg_reflect", "relation": "imports_from", "confidence": "EXTRACTED", "source_file": "D:\\code\\zero\\apps\\api\\internal\\logic\\listreviewhistorylogic_test.go", "source_location": "L4", "weight": 1.0, "context": "import"}, {"source": "d_code_zero_apps_api_internal_logic_listreviewhistorylogic_test_go", "target": "go_pkg_strings", "relation": "imports_from", "confidence": "EXTRACTED", "source_file": "D:\\code\\zero\\apps\\api\\internal\\logic\\listreviewhistorylogic_test.go", "source_location": "L5", "weight": 1.0, "context": "import"}, {"source": "d_code_zero_apps_api_internal_logic_listreviewhistorylogic_test_go", "target": "go_pkg_testing", "relation": "imports_from", "confidence": "EXTRACTED", "source_file": "D:\\code\\zero\\apps\\api\\internal\\logic\\listreviewhistorylogic_test.go", "source_location": "L6", "weight": 1.0, "context": "import"}, {"source": "d_code_zero_apps_api_internal_logic_listreviewhistorylogic_test_go", "target": "go_pkg_api_internal_types", "relation": "imports_from", "confidence": "EXTRACTED", "source_file": "D:\\code\\zero\\apps\\api\\internal\\logic\\listreviewhistorylogic_test.go", "source_location": "L8", "weight": 1.0, "context": "import"}, {"source": "d_code_zero_apps_api_internal_logic_listreviewhistorylogic_test_go", "target": "logic_listreviewhistorylogic_test_testbuildreviewhistorylistquerywithoutfilters", "relation": "contains", "confidence": "EXTRACTED", "source_file": "D:\\code\\zero\\apps\\api\\internal\\logic\\listreviewhistorylogic_test.go", "source_location": "L11", "weight": 1.0}, {"source": "d_code_zero_apps_api_internal_logic_listreviewhistorylogic_test_go", "target": "logic_listreviewhistorylogic_test_testbuildreviewhistorylistquerywithfilters", "relation": "contains", "confidence": "EXTRACTED", "source_file": "D:\\code\\zero\\apps\\api\\internal\\logic\\listreviewhistorylogic_test.go", "source_location": "L25", "weight": 1.0}], "raw_calls": [{"caller_nid": "logic_listreviewhistorylogic_test_testbuildreviewhistorylistquerywithoutfilters", "callee": "buildReviewHistoryListQuery", "is_member_call": false, "source_file": "D:\\code\\zero\\apps\\api\\internal\\logic\\listreviewhistorylogic_test.go", "source_location": "L12"}, {"caller_nid": "logic_listreviewhistorylogic_test_testbuildreviewhistorylistquerywithoutfilters", "callee": "Contains", "is_member_call": false, "source_file": "D:\\code\\zero\\apps\\api\\internal\\logic\\listreviewhistorylogic_test.go", "source_location": "L14"}, {"caller_nid": "logic_listreviewhistorylogic_test_testbuildreviewhistorylistquerywithoutfilters", "callee": "Fatalf", "is_member_call": true, "source_file": "D:\\code\\zero\\apps\\api\\internal\\logic\\listreviewhistorylogic_test.go", "source_location": "L15"}, {"caller_nid": "logic_listreviewhistorylogic_test_testbuildreviewhistorylistquerywithoutfilters", "callee": "Contains", "is_member_call": false, "source_file": "D:\\code\\zero\\apps\\api\\internal\\logic\\listreviewhistorylogic_test.go", "source_location": "L17"}, {"caller_nid": "logic_listreviewhistorylogic_test_testbuildreviewhistorylistquerywithoutfilters", "callee": "Fatalf", "is_member_call": true, "source_file": "D:\\code\\zero\\apps\\api\\internal\\logic\\listreviewhistorylogic_test.go", "source_location": "L18"}, {"caller_nid": "logic_listreviewhistorylogic_test_testbuildreviewhistorylistquerywithoutfilters", "callee": "DeepEqual", "is_member_call": false, "source_file": "D:\\code\\zero\\apps\\api\\internal\\logic\\listreviewhistorylogic_test.go", "source_location": "L20"}, {"caller_nid": "logic_listreviewhistorylogic_test_testbuildreviewhistorylistquerywithoutfilters", "callee": "uint64", "is_member_call": false, "source_file": "D:\\code\\zero\\apps\\api\\internal\\logic\\listreviewhistorylogic_test.go", "source_location": "L20"}, {"caller_nid": "logic_listreviewhistorylogic_test_testbuildreviewhistorylistquerywithoutfilters", "callee": "Fatalf", "is_member_call": true, "source_file": "D:\\code\\zero\\apps\\api\\internal\\logic\\listreviewhistorylogic_test.go", "source_location": "L21"}, {"caller_nid": "logic_listreviewhistorylogic_test_testbuildreviewhistorylistquerywithfilters", "callee": "buildReviewHistoryListQuery", "is_member_call": false, "source_file": "D:\\code\\zero\\apps\\api\\internal\\logic\\listreviewhistorylogic_test.go", "source_location": "L32"}, {"caller_nid": "logic_listreviewhistorylogic_test_testbuildreviewhistorylistquerywithfilters", "callee": "Contains", "is_member_call": false, "source_file": "D:\\code\\zero\\apps\\api\\internal\\logic\\listreviewhistorylogic_test.go", "source_location": "L43"}, {"caller_nid": "logic_listreviewhistorylogic_test_testbuildreviewhistorylistquerywithfilters", "callee": "Fatalf", "is_member_call": true, "source_file": "D:\\code\\zero\\apps\\api\\internal\\logic\\listreviewhistorylogic_test.go", "source_location": "L44"}, {"caller_nid": "logic_listreviewhistorylogic_test_testbuildreviewhistorylistquerywithfilters", "callee": "uint64", "is_member_call": false, "source_file": "D:\\code\\zero\\apps\\api\\internal\\logic\\listreviewhistorylogic_test.go", "source_location": "L49"}, {"caller_nid": "logic_listreviewhistorylogic_test_testbuildreviewhistorylistquerywithfilters", "callee": "DeepEqual", "is_member_call": false, "source_file": "D:\\code\\zero\\apps\\api\\internal\\logic\\listreviewhistorylogic_test.go", "source_location": "L60"}, {"caller_nid": "logic_listreviewhistorylogic_test_testbuildreviewhistorylistquerywithfilters", "callee": "Fatalf", "is_member_call": true, "source_file": "D:\\code\\zero\\apps\\api\\internal\\logic\\listreviewhistorylogic_test.go", "source_location": "L61"}]}