{"nodes": [{"id": "d_code_zero_apps_api_internal_config_config_test_go", "label": "config_test.go", "file_type": "code", "source_file": "D:\\code\\zero\\apps\\api\\internal\\config\\config_test.go", "source_location": "L1"}, {"id": "config_config_test_testloadsupportslegacynumericcycle", "label": "TestLoadSupportsLegacyNumericCycle()", "file_type": "code", "source_file": "D:\\code\\zero\\apps\\api\\internal\\config\\config_test.go", "source_location": "L9"}, {"id": "config_config_test_testloadsupportsstructuredcycle", "label": "TestLoadSupportsStructuredCycle()", "file_type": "code", "source_file": "D:\\code\\zero\\apps\\api\\internal\\config\\config_test.go", "source_location": "L27"}], "edges": [{"source": "d_code_zero_apps_api_internal_config_config_test_go", "target": "go_pkg_os", "relation": "imports_from", "confidence": "EXTRACTED", "source_file": "D:\\code\\zero\\apps\\api\\internal\\config\\config_test.go", "source_location": "L4", "weight": 1.0, "context": "import"}, {"source": "d_code_zero_apps_api_internal_config_config_test_go", "target": "go_pkg_path_filepath", "relation": "imports_from", "confidence": "EXTRACTED", "source_file": "D:\\code\\zero\\apps\\api\\internal\\config\\config_test.go", "source_location": "L5", "weight": 1.0, "context": "import"}, {"source": "d_code_zero_apps_api_internal_config_config_test_go", "target": "go_pkg_testing", "relation": "imports_from", "confidence": "EXTRACTED", "source_file": "D:\\code\\zero\\apps\\api\\internal\\config\\config_test.go", "source_location": "L6", "weight": 1.0, "context": "import"}, {"source": "d_code_zero_apps_api_internal_config_config_test_go", "target": "config_config_test_testloadsupportslegacynumericcycle", "relation": "contains", "confidence": "EXTRACTED", "source_file": "D:\\code\\zero\\apps\\api\\internal\\config\\config_test.go", "source_location": "L9", "weight": 1.0}, {"source": "d_code_zero_apps_api_internal_config_config_test_go", "target": "config_config_test_testloadsupportsstructuredcycle", "relation": "contains", "confidence": "EXTRACTED", "source_file": "D:\\code\\zero\\apps\\api\\internal\\config\\config_test.go", "source_location": "L27", "weight": 1.0}], "raw_calls": [{"caller_nid": "config_config_test_testloadsupportslegacynumericcycle", "callee": "TempDir", "is_member_call": true, "source_file": "D:\\code\\zero\\apps\\api\\internal\\config\\config_test.go", "source_location": "L10"}, {"caller_nid": "config_config_test_testloadsupportslegacynumericcycle", "callee": "Join", "is_member_call": false, "source_file": "D:\\code\\zero\\apps\\api\\internal\\config\\config_test.go", "source_location": "L11"}, {"caller_nid": "config_config_test_testloadsupportslegacynumericcycle", "callee": "WriteFile", "is_member_call": false, "source_file": "D:\\code\\zero\\apps\\api\\internal\\config\\config_test.go", "source_location": "L13"}, {"caller_nid": "config_config_test_testloadsupportslegacynumericcycle", "callee": "Fatalf", "is_member_call": true, "source_file": "D:\\code\\zero\\apps\\api\\internal\\config\\config_test.go", "source_location": "L14"}, {"caller_nid": "config_config_test_testloadsupportslegacynumericcycle", "callee": "Load", "is_member_call": false, "source_file": "D:\\code\\zero\\apps\\api\\internal\\config\\config_test.go", "source_location": "L18"}, {"caller_nid": "config_config_test_testloadsupportslegacynumericcycle", "callee": "Fatalf", "is_member_call": true, "source_file": "D:\\code\\zero\\apps\\api\\internal\\config\\config_test.go", "source_location": "L19"}, {"caller_nid": "config_config_test_testloadsupportslegacynumericcycle", "callee": "Fatalf", "is_member_call": true, "source_file": "D:\\code\\zero\\apps\\api\\internal\\config\\config_test.go", "source_location": "L23"}, {"caller_nid": "config_config_test_testloadsupportsstructuredcycle", "callee": "TempDir", "is_member_call": true, "source_file": "D:\\code\\zero\\apps\\api\\internal\\config\\config_test.go", "source_location": "L28"}, {"caller_nid": "config_config_test_testloadsupportsstructuredcycle", "callee": "Join", "is_member_call": false, "source_file": "D:\\code\\zero\\apps\\api\\internal\\config\\config_test.go", "source_location": "L29"}, {"caller_nid": "config_config_test_testloadsupportsstructuredcycle", "callee": "WriteFile", "is_member_call": false, "source_file": "D:\\code\\zero\\apps\\api\\internal\\config\\config_test.go", "source_location": "L31"}, {"caller_nid": "config_config_test_testloadsupportsstructuredcycle", "callee": "Fatalf", "is_member_call": true, "source_file": "D:\\code\\zero\\apps\\api\\internal\\config\\config_test.go", "source_location": "L32"}, {"caller_nid": "config_config_test_testloadsupportsstructuredcycle", "callee": "Load", "is_member_call": false, "source_file": "D:\\code\\zero\\apps\\api\\internal\\config\\config_test.go", "source_location": "L36"}, {"caller_nid": "config_config_test_testloadsupportsstructuredcycle", "callee": "Fatalf", "is_member_call": true, "source_file": "D:\\code\\zero\\apps\\api\\internal\\config\\config_test.go", "source_location": "L37"}, {"caller_nid": "config_config_test_testloadsupportsstructuredcycle", "callee": "Fatalf", "is_member_call": true, "source_file": "D:\\code\\zero\\apps\\api\\internal\\config\\config_test.go", "source_location": "L41"}]}